docs/source/conf.py
docs/source/features/code_blocks/guideline_iterator/graph.py
docs/source/features/code_blocks/interventions/fixed_value_do.py
docs/source/features/code_blocks/interventions/functional_do.py
docs/source/features/code_blocks/interventions/self_do.py
docs/source/features/code_blocks/m_graphs/graph.py
docs/source/features/code_blocks/m_graphs/miss_mechanisms.py
docs/source/features/code_blocks/temporal/customs.py
docs/source/features/code_blocks/temporal/main.py
docs/source/features/code_blocks/temporal/temporal_graph.py
docs/source/getting_started/code_blocks/img_scripts_arctan.py
docs/source/getting_started/code_blocks/img_scripts_rbf.py
docs/source/getting_started/code_blocks/img_scripts_sigmoid.py
docs/source/getting_started/code_blocks/first_graph/desc.py
docs/source/getting_started/code_blocks/first_graph/errors_1.py
docs/source/getting_started/code_blocks/first_graph/errors_2.py
docs/source/getting_started/code_blocks/first_graph/errors_3.py
docs/source/getting_started/code_blocks/first_graph/graph.py
docs/source/getting_started/code_blocks/first_graph/infer_edge_error.py
docs/source/getting_started/code_blocks/first_graph/infer_edge_true.py
docs/source/getting_started/code_blocks/first_graph/main.py
docs/source/getting_started/code_blocks/nodes_and_edges/const.py
docs/source/getting_started/code_blocks/nodes_and_edges/correction_1.py
docs/source/getting_started/code_blocks/nodes_and_edges/correction_2.py
docs/source/getting_started/code_blocks/nodes_and_edges/correction_3.py
docs/source/getting_started/code_blocks/nodes_and_edges/correction_4.py
docs/source/getting_started/code_blocks/nodes_and_edges/custom_functions.py
docs/source/getting_started/code_blocks/nodes_and_edges/data.py
docs/source/getting_started/code_blocks/nodes_and_edges/data_2.py
docs/source/getting_started/code_blocks/nodes_and_edges/deterministic.py
docs/source/getting_started/code_blocks/nodes_and_edges/dummy.py
pyparcs-1.0.0.dist-info/LICENSE.txt
pyparcs-1.0.0.dist-info/METADATA
pyparcs-1.0.0.dist-info/WHEEL
pyparcs-1.0.0.dist-info/entry_points.txt
pyparcs-1.0.0.dist-info/top_level.txt
pyparcs-1.0.0.dist-info/RECORD
