Metadata-Version: 2.1
Name: pyparcs
Version: 1.0.0
Summary: A simulation package for causal methods
Author-email: Alireza Zamanian <alireza.zamanian@iks.fraunhofer.de>, Ruijie Chen <ruijie.chen@iks.fraunhofer.de>, Leopold Mareis <leopold.mareis@iks.fraunhofer.de>
Maintainer-email: Alireza Zamanian <alireza.zamanian@iks.fraunhofer.de>
License: GNU GENERAL PUBLIC LICENSE
Project-URL: documentation, https://fraunhoferiks.github.io/parcs/
Project-URL: repository, https://github.com/FraunhoferIKS/parcs
Keywords: simulation,causal inference,directed acyclic graphs
Classifier: Development Status :: 4 - Beta
Classifier: Intended Audience :: Education
Classifier: Intended Audience :: Science/Research
Classifier: License :: OSI Approved :: GNU General Public License v2 or later (GPLv2+)
Classifier: Topic :: Scientific/Engineering :: Mathematics
Requires-Python: >=3.8
License-File: LICENSE.txt
Requires-Dist: numpy ~=1.22.2
Requires-Dist: pandas ~=1.3.3
Requires-Dist: scipy
Requires-Dist: scikit-learn ~=1.0.2
Requires-Dist: PyYAML ~=6.0
Requires-Dist: typeguard ~=2.13.3
Requires-Dist: cycler ~=0.11.0
Requires-Dist: typing ~=3.7.4.3
Requires-Dist: python-benedict ~=0.32.0
Requires-Dist: matplotlib ~=3.5.1
Provides-Extra: doc
Requires-Dist: sphinx ; extra == 'doc'
Provides-Extra: test
Requires-Dist: pytest ; extra == 'test'
